grove_keeper/__init__.py
grove_keeper/cli.py
grove_keeper/funcmodule.py
grove_keeper-0.1.3.dist-info/entry_points.txt
grove_keeper-0.1.3.dist-info/LICENSE
grove_keeper-0.1.3.dist-info/WHEEL
grove_keeper-0.1.3.dist-info/METADATA
grove_keeper-0.1.3.dist-info/RECORD
