Metadata-Version: 2.1
Name: grove-keeper
Version: 0.1.3
Summary: A simple password manager to be used with Good Bot.
License: MIT
Author: tricky
Author-email: etienne.parent@beon.ca
Requires-Python: >=3.7,<4.0
Classifier: Development Status :: 3 - Alpha
Classifier: License :: OSI Approved :: MIT License
Classifier: Natural Language :: English
Classifier: Operating System :: POSIX
Classifier: Programming Language :: Python :: 3
Classifier: Programming Language :: Python :: 3.7
Classifier: Programming Language :: Python :: 3.8
Requires-Dist: click (>=7.1.2,<8.0.0)
Requires-Dist: cryptography (>=2.9.2,<3.0.0)
